{"date": "2026-05-04", "rows": [{"Channel": "Paid Search", "Sessions": 1193, "Users": 1054, "Conversions": 0.0, "Engagement Rate (%)": 67.6, "Avg. Session (s)": 134.7, "Whatsapp LP": 131, "Generate Lead": 4}, {"Channel": "Cross-network", "Sessions": 1044, "Users": 866, "Conversions": 0.0, "Engagement Rate (%)": 62.5, "Avg. Session (s)": 220.3, "Whatsapp LP": 112, "Generate Lead": 0}, {"Channel": "Direct", "Sessions": 430, "Users": 417, "Conversions": 0.0, "Engagement Rate (%)": 82.6, "Avg. Session (s)": 89.4, "Whatsapp LP": 73, "Generate Lead": 1}, {"Channel": "Unassigned", "Sessions": 112, "Users": 109, "Conversions": 0.0, "Engagement Rate (%)": 0.9, "Avg. Session (s)": 291.3, "Whatsapp LP": 23, "Generate Lead": 0}, {"Channel": "Organic Search", "Sessions": 101, "Users": 87, "Conversions": 0.0, "Engagement Rate (%)": 69.3, "Avg. Session (s)": 149.4, "Whatsapp LP": 13, "Generate Lead": 0}, {"Channel": "Referral", "Sessions": 33, "Users": 28, "Conversions": 0.0, "Engagement Rate (%)": 72.7, "Avg. Session (s)": 180.5, "Whatsapp LP": 6, "Generate Lead": 0}, {"Channel": "Organic Social", "Sessions": 4, "Users": 3, "Conversions": 0.0, "Engagement Rate (%)": 75.0, "Avg. Session (s)": 91.1, "Whatsapp LP": 1, "Generate Lead": 0}]}