{"date": "2026-05-07", "rows": [{"Page": "/vestidos-de-noivas", "Pageviews": 247, "Avg. Session (s)": 97.0, "Conversions": 0, "Whatsapp LP": 34, "Generate Lead": 0}, {"Page": "/", "Pageviews": 140, "Avg. Session (s)": 136.0, "Conversions": 0, "Whatsapp LP": 4, "Generate Lead": 0}, {"Page": "/blank-1", "Pageviews": 2, "Avg. Session (s)": 68.0, "Conversions": 0, "Whatsapp LP": 0, "Generate Lead": 0}, {"Page": "/vestido-de-festas", "Pageviews": 1, "Avg. Session (s)": 51.0, "Conversions": 0, "Whatsapp LP": 5, "Generate Lead": 0}, {"Page": "/15anos-teste", "Pageviews": 0, "Avg. Session (s)": 79.0, "Conversions": 0, "Whatsapp LP": 2, "Generate Lead": 0}]}